pylib.py
pyScripts/__init__.py
pyScripts/change_ssh_hotstart.py
pyScripts/download_AVISO.py
pyScripts/download_CMEMS.py
pyScripts/download_HFRadar.py
pyScripts/download_hycom.py
pyScripts/gen_bctides.py
pyScripts/gen_fluxflag.py
pyScripts/gen_fluxth_USGS.py
pyScripts/gen_hycom_3Dth_nudge.py
pyScripts/gen_hycom_hotstart.py
pyScripts/gen_narr_sflux.py
pyScripts/gen_shapiro.py
pyScripts/gen_vqs.py
pyScripts/hotstart_proc.py
pyScripts/make_sflux_links.py
pyScripts/make_sflux_subdomain.py
pyScripts/pextract_OLDIO_schism_fabm_xyz.py
pyScripts/pextract_OLDIO_schism_tide.py
pyScripts/pextract_schism.py
pyScripts/pextract_schism_flux.py
pyScripts/pextract_schism_slab.py
pyScripts/pload_dem.py
pyScripts/pload_depth.py
pyScripts/prj.npz
pyScripts/pschism_output_subset.py
pyScripts/run_mpi_template.py
pyScripts/schismcheck
pyScripts/schismview
pyScripts/sflux_template.npz
pyScripts/subset_outputs_parallel.py
pyScripts/Harmonic_Analysis/compile.py
pyScripts/Harmonic_Analysis/nrutil.c
pyScripts/Harmonic_Analysis/nrutil.h
pyScripts/Harmonic_Analysis/readme.txt
pyScripts/Harmonic_Analysis/tidal_analysis.c
pyScripts/Harmonic_Analysis/tidal_analyze
pyScripts/Harmonic_Analysis/tidal_const.dat
pyScripts/Harmonic_Analysis/tide_fac_const.npz
pyUtility/__init__.py
pyUtility/mylib.py
pyUtility/schism_file.py
pylibs/scripts/__init__.py
pylibs/scripts/change_ssh_hotstart.py
pylibs/scripts/download_AVISO.py
pylibs/scripts/download_CMEMS.py
pylibs/scripts/download_HFRadar.py
pylibs/scripts/download_hycom.py
pylibs/scripts/gen_bctides.py
pylibs/scripts/gen_fluxflag.py
pylibs/scripts/gen_fluxth_USGS.py
pylibs/scripts/gen_hycom_3Dth_nudge.py
pylibs/scripts/gen_hycom_hotstart.py
pylibs/scripts/gen_narr_sflux.py
pylibs/scripts/gen_shapiro.py
pylibs/scripts/gen_vqs.py
pylibs/scripts/hotstart_proc.py
pylibs/scripts/make_sflux_links.py
pylibs/scripts/make_sflux_subdomain.py
pylibs/scripts/pextract_OLDIO_schism_fabm_xyz.py
pylibs/scripts/pextract_OLDIO_schism_tide.py
pylibs/scripts/pextract_schism.py
pylibs_ocean-1.2.3.dist-info/LICENSE
pylibs_ocean-1.2.3.dist-info/METADATA
pylibs_ocean-1.2.3.dist-info/WHEEL
pylibs_ocean-1.2.3.dist-info/top_level.txt
pylibs_ocean-1.2.3.dist-info/RECORD
