Metadata-Version: 2.1
Name: pylibs_ocean
Version: 1.2.3
Summary: python tools for ocean reserach
Home-page: https://github.com/wzhengui/pylibs
Author: Zhengui Wang
Author-email: wzhengui@gmail.com
License-File: LICENSE
Requires-Dist: setuptools
Requires-Dist: pandas
Requires-Dist: numpy
Requires-Dist: netCDF4 >=1.5.8
Requires-Dist: matplotlib >=3.0.0
Requires-Dist: scipy
Provides-Extra: all
Requires-Dist: mpi4py >=3.0.0 ; extra == 'all'
Requires-Dist: pyshp >=2.1.0 ; extra == 'all'
Requires-Dist: pyproj >=3.0.0 ; extra == 'all'
Requires-Dist: eofs >=1.4.0 ; extra == 'all'
Requires-Dist: cloudpickle ==2.2.1 ; extra == 'all'
Requires-Dist: tifffile ==2022.5.4 ; extra == 'all'
Requires-Dist: imagecodecs ==2024.6.1 ; extra == 'all'
Requires-Dist: urllib3 ==2.2.1 ; extra == 'all'
Requires-Dist: basemap ==1.4.1 ; extra == 'all'
Requires-Dist: basemap-data-hires ==1.3.2 ; extra == 'all'
Provides-Extra: basemap
Requires-Dist: basemap ==1.4.1 ; extra == 'basemap'
Requires-Dist: basemap-data-hires ==1.3.2 ; extra == 'basemap'
Provides-Extra: cloudpickle
Requires-Dist: cloudpickle ==2.2.1 ; extra == 'cloudpickle'
Provides-Extra: eof
Requires-Dist: eofs >=1.4.0 ; extra == 'eof'
Provides-Extra: mpi
Requires-Dist: mpi4py >=3.0.0 ; extra == 'mpi'
Provides-Extra: projection
Requires-Dist: pyproj >=3.0.0 ; extra == 'projection'
Provides-Extra: shapefile
Requires-Dist: pyshp >=2.1.0 ; extra == 'shapefile'
Provides-Extra: tiff
Requires-Dist: tifffile ==2022.5.4 ; extra == 'tiff'
Requires-Dist: imagecodecs ==2024.6.1 ; extra == 'tiff'
Provides-Extra: urllib
Requires-Dist: urllib3 ==2.2.1 ; extra == 'urllib'
